node_events/__init__.py
node_events-0.6.9.dist-info/LICENSE
node_events-0.6.9.dist-info/METADATA
node_events-0.6.9.dist-info/WHEEL
node_events-0.6.9.dist-info/top_level.txt
node_events-0.6.9.dist-info/RECORD
