Metadata-Version: 2.1
Name: node-events
Version: 0.6.9
Summary: A minor rewrite of the NodeJS EventEmitter in Python
Home-page: https://github.com/miraclx/node_events.py
Author: Miraculous Owonubi
Author-email: omiraculous@gmail.com
License: Apache-2.0
Platform: UNKNOWN
Classifier: Operating System :: OS Independent
Classifier: Programming Language :: Python :: 3
Classifier: License :: OSI Approved :: Apache Software License
